django_easy_thumbnails_watermark_1-0.7.0.dist-info/DESCRIPTION.rst
django_easy_thumbnails_watermark_1-0.7.0.dist-info/METADATA
django_easy_thumbnails_watermark_1-0.7.0.dist-info/RECORD
django_easy_thumbnails_watermark_1-0.7.0.dist-info/WHEEL
django_easy_thumbnails_watermark_1-0.7.0.dist-info/metadata.json
django_easy_thumbnails_watermark_1-0.7.0.dist-info/top_level.txt
easy_thumbnails_watermark/__init__.py
easy_thumbnails_watermark/models.py
easy_thumbnails_watermark/thumbnail_processors.py
