Metadata-Version: 2.0
Name: django-easy-thumbnails-watermark-1
Version: 0.7.0
Summary: A watermark filter for easy_thumbnails
Home-page: https://github.com/frague59/django-easy-thumbnails-watermark
Author: Davide Riccardo Caliendo
Author-email: frague59@gmail.com
License: GPLv3 License
Platform: UNKNOWN
Classifier: Environment :: Web Environment
Classifier: Framework :: Django
Classifier: Intended Audience :: Developers
Classifier: License :: OSI Approved :: GNU General Public License v3 (GPLv3)
Classifier: Operating System :: OS Independent
Classifier: Programming Language :: Python
Classifier: Programming Language :: Python :: 2.6
Classifier: Programming Language :: Python :: 2.7
Classifier: Programming Language :: Python :: 3.4
Classifier: Programming Language :: Python :: 3.5
Classifier: Programming Language :: Python :: 3.6
Classifier: Topic :: Internet :: WWW/HTTP
Classifier: Topic :: Internet :: WWW/HTTP :: Dynamic Content
Requires-Dist: easy-thumbnails
